djangocms_hubspot_blog/tests.py
djangocms_hubspot_blog/__init__.py
djangocms_hubspot_blog/models.py
djangocms_hubspot_blog/views.py
djangocms_hubspot_blog/admin.py
djangocms_hubspot_blog/urls.py
djangocms_hubspot_blog/apps.py
djangocms_hubspot_blog/hubspot_api.py
djangocms_hubspot_blog/cms_apps.py
djangocms_hubspot_blog-0.2.1.dist-info/metadata.json
djangocms_hubspot_blog-0.2.1.dist-info/RECORD
djangocms_hubspot_blog-0.2.1.dist-info/top_level.txt
djangocms_hubspot_blog-0.2.1.dist-info/METADATA
djangocms_hubspot_blog-0.2.1.dist-info/DESCRIPTION.rst
djangocms_hubspot_blog-0.2.1.dist-info/WHEEL
