Metadata-Version: 2.0
Name: djangocms-hubspot-blog
Version: 0.2.1
Summary: A djangoCMS App which imports blog posts from the Hubspot Content API
Home-page: https://github.com/Blueshoe/djangocms-hubspot-blog
Author: Maximilian Muth
Author-email: max@blueshoe.de
License: MIT License
Requires-Dist: django (>=1.8,<2.0)
Requires-Dist: django-cms (>=3.2)
Requires-Dist: requests
